CHANGELOG.md
LICENSE
MANIFEST.in
README.md
setup.cfg
setup.py
caribbean_outbreak_tracker.egg-info/PKG-INFO
caribbean_outbreak_tracker.egg-info/SOURCES.txt
caribbean_outbreak_tracker.egg-info/dependency_links.txt
caribbean_outbreak_tracker.egg-info/requires.txt
caribbean_outbreak_tracker.egg-info/top_level.txt
docs/Makefile
docs/make.bat
docs/source/conf.py
docs/source/index.rst
outbreak_tracker/__init__.py
outbreak_tracker/admin.py
outbreak_tracker/apps.py
outbreak_tracker/models.py
outbreak_tracker/views.py
outbreak_tracker/migrations/__init__.py
outbreak_tracker/templates/outbreak_tracker/all_islands.html
outbreak_tracker/templates/outbreak_tracker/island.html
outbreak_tracker/templatetags/__init__.py
outbreak_tracker/templatetags/outbreak_tracker_tags.py